[
    {
      "nombre" : " LINEA" ,
      "imagen" : " imagenes/patines/linea.png"
    },
    {
      "nombre" : " QUADS " ,
      "imagen" : " imagenes/patines/Quads.jpg"
    },
    {
      "nombre" : " SCOOTER " ,
      "imagen" : " imagenes/patines/scooter.png"
    },
    {
      "nombre" : " HIELO" ,
      "imagen" : " imagenes/patines/hielo.jpg "
    },
    {
      "nombre" : " SKATES " ,
      "imagen" : " imagenes/patines/skates.png " 
    },
    {
      "nombre" : " ROPA",
      "imagen" : " imagenes/patines/ropa.png " 
    },
    {
      "nombre" : " PROTECCIONES " ,
      "imagen" : " imagenes/patines/protecciones.png "
    },
    {
      "nombre" : " TENIS " ,
      "imagen" : " imagenes/patines/tenis.png "
    }
  ]